{
  "name": "GreenBus - Автобусные билеты онлайн",
  "short_name": "GreenBus",
  "description": "Бронирование автобусных билетов по Украине и Европе",
  "start_url": "/",
  "scope": "/",
  "display": "standalone",
  "orientation": "portrait-primary",
  "theme_color": "#018f37",
  "background_color": "#ffffff",
  "lang": "uk",
  "dir": "ltr",
  "categories": ["travel", "transportation", "business"],
  "icons": [
    {
      "src": "/my-favicon/web-app-manifest-192x192.png",
      "sizes": "192x192",
      "type": "image/png",
      "purpose": "maskable"
    },
    {
      "src": "/my-favicon/web-app-manifest-512x512.png",
      "sizes": "512x512",
      "type": "image/png",
      "purpose": "maskable"
    },
    {
      "src": "/my-favicon/web-app-manifest-192x192.png",
      "sizes": "192x192",
      "type": "image/png",
      "purpose": "any"
    },
    {
      "src": "/my-favicon/web-app-manifest-512x512.png",
      "sizes": "512x512",
      "type": "image/png",
      "purpose": "any"
    },
    {
      "src": "/my-favicon/apple-touch-icon-180x180.png",
      "sizes": "180x180",
      "type": "image/png",
      "purpose": "any"
    }
  ],
  "shortcuts": [
    {
      "name": "Поиск автобусов",
      "short_name": "Поиск",
      "description": "Найти автобусные маршруты",
      "url": "/buses",
      "icons": [
        {
          "src": "/my-favicon/web-app-manifest-192x192.png",
          "sizes": "192x192"
        }
      ]
    },
    {
      "name": "Мои заказы",
      "short_name": "Заказы",
      "description": "Просмотреть историю заказов",
      "url": "/orders",
      "icons": [
        {
          "src": "/my-favicon/web-app-manifest-192x192.png",
          "sizes": "192x192"
        }
      ]
    }
  ],
  "screenshots": [
    {
      "src": "/screenshots/desktop-1.png",
      "sizes": "1280x720",
      "type": "image/png",
      "form_factor": "wide",
      "label": "Главная страница GreenBus"
    },
    {
      "src": "/screenshots/mobile-1.png",
      "sizes": "390x844",
      "type": "image/png",
      "form_factor": "narrow",
      "label": "Поиск автобусов на мобильном"
    }
  ]
}
